arnablog/__init__.py
arnablog/add_to_changelog.py
arnablog-0.2.dist-info/METADATA
arnablog-0.2.dist-info/WHEEL
arnablog-0.2.dist-info/entry_points.txt
arnablog-0.2.dist-info/top_level.txt
arnablog-0.2.dist-info/RECORD
