Metadata-Version: 2.2
Name: arnablog
Version: 0.2
Summary: A CLI tool to add entries to a changelog file
Author: Your Name
Classifier: Programming Language :: Python :: 3
Classifier: License :: OSI Approved :: MIT License
Classifier: Operating System :: OS Independent
Requires-Python: >=3.6
Dynamic: author
Dynamic: classifier
Dynamic: requires-python
Dynamic: summary
